CONTRIBUTORS.txt
MANIFEST.in
README.rst
requirements.txt
setup.py
tox.ini
gipsy/__init__.py
gipsy/menus/__init__.py
gipsy/menus/admin.py
gipsy/menus/admin_base.py
gipsy/menus/apps.py
gipsy/menus/forms.py
gipsy/menus/forms_base.py
gipsy/menus/managers.py
gipsy/menus/managers_base.py
gipsy/menus/models.py
gipsy/menus/models_base.py
gipsy/menus/tests.py
gipsy/menus/views.py
gipsy/menus/migrations/0001_initial.py
gipsy/menus/migrations/0002_auto_20150723_0921.py
gipsy/menus/migrations/0003_auto_20150723_0923.py
gipsy/menus/migrations/0004_auto_20150723_1551.py
gipsy/menus/migrations/__init__.py
gipsy/menus/templatetags/__init__.py
gipsy/menus/templatetags/gipsy_menus.py
gipsy/menus/templatetags/gipsy_menus_base.py
gipsy_menus.egg-info/PKG-INFO
gipsy_menus.egg-info/SOURCES.txt
gipsy_menus.egg-info/dependency_links.txt
gipsy_menus.egg-info/namespace_packages.txt
gipsy_menus.egg-info/not-zip-safe
gipsy_menus.egg-info/pbr.json
gipsy_menus.egg-info/requires.txt
gipsy_menus.egg-info/top_level.txt
requirements/base.txt
requirements/dev.txt
requirements/production.txt
requirements/test.txt